{
  "db_name": "PostgreSQL",
  "query": "SELECT\n            id,\n            provider_id,\n            name,\n            key,\n            usage_count,\n            enabled,\n            created_at\n         FROM provider_keys\n         WHERE provider_id = $1\n         ORDER BY created_at DESC",
  "describe": {
    "columns": [
      {
        "ordinal": 0,
        "name": "id",
        "type_info": "Uuid"
      },
      {
        "ordinal": 1,
        "name": "provider_id",
        "type_info": "Uuid"
      },
      {
        "ordinal": 2,
        "name": "name",
        "type_info": "Text"
      },
      {
        "ordinal": 3,
        "name": "key",
        "type_info": "Text"
      },
      {
        "ordinal": 4,
        "name": "usage_count",
        "type_info": "Int8"
      },
      {
        "ordinal": 5,
        "name": "enabled",
        "type_info": "Bool"
      },
      {
        "ordinal": 6,
        "name": "created_at",
        "type_info": "Timestamptz"
      }
    ],
    "parameters": {
      "Left": [
        "Uuid"
      ]
    },
    "nullable": [
      false,
      false,
      true,
      false,
      false,
      false,
      false
    ]
  },
  "hash": "0804899293e8e1c42b4a80f96ef5bf273d3a0a531b1ac986c90ea75af4f9a64a"
}
